{
  "_buildCommand2" : {
    "command" : "prepareForIndexing",
    "enableIndexBuildArena" : true,
    "targets" : null
  },
  "buildCommand" : "build",
  "configuredTargets" : [
    {
      "guid" : "e4f3b12c3493db7030fcb769af82344b5efca277d056dacf954f29913427f28a"
    }
  ],
  "containerPath" : "/Users/IpoAbe/Documents/Xcode/GameClock/GameClock.xcodeproj",
  "continueBuildingAfterErrors" : true,
  "enableIndexBuildArena" : false,
  "hideShellScriptEnvironment" : false,
  "parameters" : {
    "action" : "indexbuild",
    "activeArchitecture" : "arm64e",
    "activeRunDestination" : {
      "disableOnlyActiveArch" : true,
      "platform" : "iphoneos",
      "sdk" : "iphoneos15.5",
      "sdkVariant" : "iphoneos",
      "supportedArchitectures" : [
        "armv4t",
        "armv5",
        "armv6",
        "armv7",
        "armv7f",
        "armv7s",
        "armv7k",
        "arm64",
        "arm64e"
      ],
      "targetArchitecture" : "arm64e"
    },
    "arenaInfo" : {
      "buildIntermediatesPath" : "/Users/IpoAbe/Documents/Xcode/GameClock/DerivedData/GameClock/Index/Build/Intermediates.noindex",
      "buildProductsPath" : "/Users/IpoAbe/Documents/Xcode/GameClock/DerivedData/GameClock/Index/Build/Products",
      "derivedDataPath" : "/Users/IpoAbe/Documents/Xcode/GameClock/DerivedData",
      "indexDataStoreFolderPath" : "/Users/IpoAbe/Documents/Xcode/GameClock/DerivedData/GameClock/Index/DataStore",
      "indexEnableDataStore" : true,
      "indexPCHPath" : "/Users/IpoAbe/Documents/Xcode/GameClock/DerivedData/GameClock/Index/PrecompiledHeaders",
      "pchPath" : "/Users/IpoAbe/Documents/Xcode/GameClock/DerivedData/GameClock/Index/Build/Intermediates.noindex/PrecompiledHeaders"
    },
    "configurationName" : "Debug",
    "overrides" : {
      "synthesized" : {
        "table" : {
          "ENABLE_PREVIEWS" : "NO",
          "INDEX_ARENA_INFO_REGULAR_BUILD_PRODUCTS_DIR" : "/Users/IpoAbe/Documents/Xcode/GameClock/DerivedData/GameClock/Build/Products",
          "ONLY_ACTIVE_ARCH" : "YES"
        }
      }
    }
  },
  "qos" : "default",
  "schemeCommand" : "launch",
  "schemeCommand2" : "launch",
  "shouldCollectMetrics" : false,
  "showNonLoggedProgress" : true,
  "useDryRun" : false,
  "useImplicitDependencies" : true,
  "useLegacyBuildLocations" : false,
  "useParallelTargets" : true
}